num_akr/__init__.py
num_akr-1.0.dist-info/METADATA
num_akr-1.0.dist-info/WHEEL
num_akr-1.0.dist-info/top_level.txt
num_akr-1.0.dist-info/RECORD
