Metadata-Version: 2.1
Name: num_akr
Version: 1.0
Author: Ameba
Requires-Dist: numpy
Requires-Dist: pyperclip
